README.md
setup.py
unifi_video/__init__.py
unifi_video/_six.py
unifi_video/_version.py
unifi_video/api.py
unifi_video/camera.py
unifi_video/collections.py
unifi_video/recording.py
unifi_video/single.py
unifi_video/utils.py
unifi_video.egg-info/PKG-INFO
unifi_video.egg-info/SOURCES.txt
unifi_video.egg-info/dependency_links.txt
unifi_video.egg-info/top_level.txt