Metadata-Version: 2.1
Name: unifi-video
Version: 0.3.0
Summary: Python API for UniFi Video
Home-page: https://github.com/yuppity/unifi-video-api
Author: yuppity
Author-email: yuppity_pypi@wubbalubba.com
License: UNKNOWN
Platform: UNKNOWN
Classifier: Programming Language :: Python :: 2
Classifier: Programming Language :: Python :: 3
Classifier: License :: OSI Approved :: MIT License
Requires-Python: >=2.7
